odoo/addons/mail_environment_office365/README.rst
odoo/addons/mail_environment_office365/__init__.py
odoo/addons/mail_environment_office365/__manifest__.py
odoo/addons/mail_environment_office365/i18n/it.po
odoo/addons/mail_environment_office365/i18n/mail_environment_office365.pot
odoo/addons/mail_environment_office365/models/__init__.py
odoo/addons/mail_environment_office365/models/ir_mail_server.py
odoo/addons/mail_environment_office365/readme/CONFIGURE.md
odoo/addons/mail_environment_office365/readme/CONTRIBUTORS.md
odoo/addons/mail_environment_office365/readme/DESCRIPTION.md
odoo/addons/mail_environment_office365/static/description/icon.png
odoo/addons/mail_environment_office365/static/description/index.html
odoo/addons/mail_environment_office365/tests/__init__.py
odoo/addons/mail_environment_office365/tests/test_mail_environment.py
odoo_addon_mail_environment_office365-17.0.1.0.0.4.dist-info/METADATA
odoo_addon_mail_environment_office365-17.0.1.0.0.4.dist-info/WHEEL
odoo_addon_mail_environment_office365-17.0.1.0.0.4.dist-info/top_level.txt
odoo_addon_mail_environment_office365-17.0.1.0.0.4.dist-info/RECORD
