Metadata-Version: 2.1
Name: odoo-addon-mail_environment_office365
Version: 17.0.1.0.0.4
Requires-Python: >=3.10
Requires-Dist: odoo-addon-mail_environment>=17.0dev,<17.1dev
Requires-Dist: odoo-addon-server_environment_ir_config_parameter>=17.0dev,<17.1dev
Requires-Dist: odoo>=17.0a,<17.1dev
Summary: Configure Office365 parameters with environment variables via server_environment
Home-page: https://github.com/OCA/server-env
License: AGPL-3
Author: Camptocamp, Odoo Community Association (OCA)
Author-email: support@odoo-community.org
Classifier: Programming Language :: Python
Classifier: Framework :: Odoo
Classifier: Framework :: Odoo :: 17.0
Classifier: License :: OSI Approved :: GNU Affero General Public License v3
